cv2geojson/__init__.py
cv2geojson-0.0.9.dist-info/LICENSE
cv2geojson-0.0.9.dist-info/METADATA
cv2geojson-0.0.9.dist-info/WHEEL
cv2geojson-0.0.9.dist-info/top_level.txt
cv2geojson-0.0.9.dist-info/RECORD
