Metadata-Version: 2.1
Name: cv2geojson
Version: 0.0.9
Summary: Export contour annotations as geojson formatted data
Author-email: Mohsen Farzi <mhnfarzi@gmail.com>
Project-URL: Homepage, https://github.com/mfarzi/cv2geojson
Project-URL: Bug Tracker, https://github.com/mfarzi/cv2geojson/issues
Keywords: python,geojson,opencv,contours,polygons
Classifier: Development Status :: 1 - Planning
Classifier: Programming Language :: Python :: 3
Classifier: License :: OSI Approved :: MIT License
Classifier: Operating System :: OS Independent
Classifier: Intended Audience :: Developers
Classifier: Intended Audience :: Science/Research
Requires-Python: >=3.7
License-File: LICENSE
Requires-Dist: opencv-python
Requires-Dist: numpy
Requires-Dist: geojson
